{
  "className": "PertFigure",
  "methodName": "connectionInsets",
  "brief": "public Insets connectionInsets(){}",
  "methodSignature": "connectionInsets()",
  "sourceCode": "public Insets connectionInsets() {\n        Rectangle r = fDisplayBox;\n        int cx = r.width/2;\n        int cy = r.height/2;\n        return new Insets(cy, cx, cy, cx);\n    }",
  "useField": true,
  "isConstructor": false,
  "isGetSet": false,
  "isPublic": true,
  "isBoolean": false,
  "isAbstract": false,
  "parameters": [],
  "dependentMethods": {},
  "full_method_info": "public Insets connectionInsets() {\n    Rectangle r = fDisplayBox;\n    int cx = r.width / 2;\n    int cy = r.height / 2;\n    return new Insets(cy, cx, cy, cx);\n}",
  "method_comment": "",
  "method_annotation": ""
}